{
  "name": "mitigation_cb2024-300mt-hires",
  "data": [
    {
      "seriesName": "AGRCO2N",
      "seriesValues": [
        [
          2018,
          641.038746904162
        ],
        [
          2019,
          1286.257905302979
        ],
        [
          2020,
          2017.9125914643041
        ],
        [
          2021,
          2738.718362970501
        ],
        [
          2022,
          3635.329864809833
        ],
        [
          2023,
          4415.167128711039
        ],
        [
          2024,
          5191.796345894568
        ],
        [
          2025,
          5965.228655439287
        ],
        [
          2026,
          6736.256989226208
        ],
        [
          2027,
          7504.878525529221
        ],
        [
          2028,
          8237.786249838176
        ],
        [
          2029,
          8966.312268755077
        ],
        [
          2030,
          9593.188843122382
        ],
        [
          2031,
          10219.350356680587
        ],
        [
          2032,
          10844.831197358344
        ],
        [
          2033,
          11469.252387178738
        ],
        [
          2034,
          11806.307318613697
        ],
        [
          2035,
          12068.468665017488
        ],
        [
          2036,
          12311.319423605013
        ],
        [
          2037,
          12498.075647894459
        ],
        [
          2038,
          12665.606525821044
        ],
        [
          2039,
          12814.217094201973
        ],
        [
          2040,
          12946.455546552
        ],
        [
          2041,
          13064.102448031235
        ],
        [
          2042,
          13167.250377702874
        ],
        [
          2043,
          13240.185357911363
        ],
        [
          2044,
          13294.170937727606
        ],
        [
          2045,
          13336.424827041574
        ],
        [
          2046,
          13355.068124918203
        ],
        [
          2047,
          13365.566248957093
        ],
        [
          2048,
          13375.941884804191
        ],
        [
          2049,
          13379.936369745432
        ],
        [
          2050,
          13384.005470724684
        ],
        [
          2051,
          13982.34930469459
        ]
      ]
    },
    {
      "seriesName": "INDCO2N",
      "seriesValues": [
        [
          2018,
          3552.19468227911
        ],
        [
          2019,
          6896.70064095601
        ],
        [
          2020,
          11389.24112004468
        ],
        [
          2021,
          15992.778562257688
        ],
        [
          2022,
          20616.77856809085
        ],
        [
          2023,
          22942.96032252723
        ],
        [
          2024,
          25190.992702495838
        ],
        [
          2025,
          27328.67047443804
        ],
        [
          2026,
          29307.408932815197
        ],
        [
          2027,
          31139.114350064337
        ],
        [
          2028,
          32825.93271034339
        ],
        [
          2029,
          34347.34584058333
        ],
        [
          2030,
          35997.10405367643
        ],
        [
          2031,
          37448.94744417633
        ],
        [
          2032,
          38606.21068576437
        ],
        [
          2033,
          39546.959578447466
        ],
        [
          2034,
          40257.40960965938
        ],
        [
          2035,
          40720.194947854005
        ],
        [
          2036,
          40917.989075516336
        ],
        [
          2037,
          40917.99682190028
        ],
        [
          2038,
          40917.99777260842
        ],
        [
          2039,
          40917.99870497014
        ],
        [
          2040,
          40917.999606422985
        ],
        [
          2041,
          40918.00049136694
        ],
        [
          2042,
          40918.00135567579
        ],
        [
          2043,
          40918.05614671765
        ],
        [
          2044,
          40918.289476226884
        ],
        [
          2045,
          40918.472069086994
        ],
        [
          2046,
          40918.77123389864
        ],
        [
          2047,
          40919.15765472427
        ],
        [
          2048,
          40919.43262838233
        ],
        [
          2049,
          40919.63012192541
        ],
        [
          2050,
          40919.80854972105
        ],
        [
          2051,
          40919.80471600072
        ]
      ]
    },
    {
      "seriesName": "INDCO2P",
      "seriesValues": [
        [
          2018,
          2057.87001900541
        ],
        [
          2019,
          4115.75114075747
        ],
        [
          2020,
          6184.5921757695905
        ],
        [
          2021,
          8621.33342228946
        ],
        [
          2022,
          11058.07466880942
        ],
        [
          2023,
          13115.94467041574
        ],
        [
          2024,
          15173.81467204989
        ],
        [
          2025,
          17231.684673356198
        ],
        [
          2026,
          19289.55468093403
        ],
        [
          2027,
          21347.42468270981
        ],
        [
          2028,
          23405.29469035391
        ],
        [
          2029,
          25463.16469219144
        ],
        [
          2030,
          27521.03469405701
        ],
        [
          2031,
          27829.715226512653
        ],
        [
          2032,
          28138.395747083454
        ],
        [
          2033,
          28447.076262534156
        ],
        [
          2034,
          28755.756775213144
        ],
        [
          2035,
          29064.437286335167
        ],
        [
          2036,
          29373.117796549977
        ],
        [
          2037,
          29681.798312054187
        ],
        [
          2038,
          29990.478821382934
        ],
        [
          2039,
          30299.159330476003
        ],
        [
          2040,
          30607.83983941282
        ],
        [
          2041,
          30916.520354096534
        ],
        [
          2042,
          31225.20086286358
        ],
        [
          2043,
          31533.88137156739
        ],
        [
          2044,
          31842.561880255198
        ],
        [
          2045,
          32151.242388811454
        ],
        [
          2046,
          32459.922897548247
        ],
        [
          2047,
          32768.60340631424
        ],
        [
          2048,
          33077.28391512025
        ],
        [
          2049,
          33385.96442398242
        ],
        [
          2050,
          33694.64493291303
        ],
        [
          2051,
          34003.32546640034
        ]
      ]
    },
    {
      "seriesName": "PWRCO2N",
      "seriesValues": [
        [
          2018,
          10899.9884146514
        ],
        [
          2019,
          20362.81642627567
        ],
        [
          2020,
          29305.90579818266
        ],
        [
          2021,
          39369.38697135956
        ],
        [
          2022,
          49611.54344693046
        ],
        [
          2023,
          57702.925891850464
        ],
        [
          2024,
          64778.85259465593
        ],
        [
          2025,
          71382.69782818324
        ],
        [
          2026,
          77832.24462211171
        ],
        [
          2027,
          83786.5311569805
        ],
        [
          2028,
          88551.4024080288
        ],
        [
          2029,
          90447.9926869485
        ],
        [
          2030,
          90796.9968262453
        ],
        [
          2031,
          91141.82587019852
        ],
        [
          2032,
          91486.62282420724
        ],
        [
          2033,
          91831.39114123084
        ],
        [
          2034,
          92176.21722364974
        ],
        [
          2035,
          90345.48219724953
        ],
        [
          2036,
          88517.85538074428
        ],
        [
          2037,
          86693.2591880147
        ],
        [
          2038,
          84871.75555216639
        ],
        [
          2039,
          83053.27740653635
        ],
        [
          2040,
          81237.87105415057
        ],
        [
          2041,
          79425.50159605035
        ],
        [
          2042,
          77616.14334631573
        ],
        [
          2043,
          75809.79364712638
        ],
        [
          2044,
          74006.27363141958
        ],
        [
          2045,
          72205.78822542081
        ],
        [
          2046,
          70408.28306921235
        ],
        [
          2047,
          68613.71322153445
        ],
        [
          2048,
          66822.09523740262
        ],
        [
          2049,
          65033.507771773184
        ],
        [
          2050,
          63247.91657653962
        ],
        [
          2051,
          62310.11956978968
        ]
      ]
    },
    {
      "seriesName": "RSDCO2",
      "seriesValues": [
        [
          2018,
          6714.5437014448
        ],
        [
          2019,
          13269.66868170655
        ],
        [
          2020,
          20449.00060770004
        ],
        [
          2021,
          27193.69582903761
        ],
        [
          2022,
          33180.35151432182
        ],
        [
          2023,
          38412.41138179033
        ],
        [
          2024,
          43198.35787868643
        ],
        [
          2025,
          47567.81770629695
        ],
        [
          2026,
          51290.26845412387
        ],
        [
          2027,
          54482.34590758323
        ],
        [
          2028,
          57290.99102461565
        ],
        [
          2029,
          59677.76631279994
        ],
        [
          2030,
          61644.89652297217
        ],
        [
          2031,
          63229.50498159278
        ],
        [
          2032,
          64447.80921591939
        ],
        [
          2033,
          65391.344929093444
        ],
        [
          2034,
          66072.82140142847
        ],
        [
          2035,
          66501.5991751893
        ],
        [
          2036,
          66792.2191241135
        ],
        [
          2037,
          66929.17156375998
        ],
        [
          2038,
          67064.43948547293
        ],
        [
          2039,
          67115.82530239409
        ],
        [
          2040,
          67151.36773673038
        ],
        [
          2041,
          67171.04864557313
        ],
        [
          2042,
          67174.89330047765
        ],
        [
          2043,
          67174.9044297326
        ],
        [
          2044,
          67174.91586439406
        ],
        [
          2045,
          67174.92652084884
        ],
        [
          2046,
          67174.9373095182
        ],
        [
          2047,
          67174.94864521275
        ],
        [
          2048,
          67174.95981348166
        ],
        [
          2049,
          67174.97087635373
        ],
        [
          2050,
          67174.98216173227
        ],
        [
          2051,
          67175.33976657303
        ]
      ]
    },
    {
      "seriesName": "SRVCO2N",
      "seriesValues": [
        [
          2018,
          1504.30770463607
        ],
        [
          2019,
          2961.14843264306
        ],
        [
          2020,
          4483.33490905718
        ],
        [
          2021,
          5964.38337863679
        ],
        [
          2022,
          7445.43184821587
        ],
        [
          2023,
          8943.508175210769
        ],
        [
          2024,
          10226.1417579082
        ],
        [
          2025,
          11381.05317173897
        ],
        [
          2026,
          12487.19791764131
        ],
        [
          2027,
          13578.66247090988
        ],
        [
          2028,
          14683.79860025173
        ],
        [
          2029,
          15713.39829589918
        ],
        [
          2030,
          16138.873263043117
        ],
        [
          2031,
          16387.94795591475
        ],
        [
          2032,
          16633.66913702184
        ],
        [
          2033,
          16875.85457373426
        ],
        [
          2034,
          17113.029064875853
        ],
        [
          2035,
          17305.43044271127
        ],
        [
          2036,
          17450.6667916552
        ],
        [
          2037,
          17565.927696717004
        ],
        [
          2038,
          17664.106501593593
        ],
        [
          2039,
          17739.871832299166
        ],
        [
          2040,
          17791.89105309596
        ],
        [
          2041,
          17818.05565561543
        ],
        [
          2042,
          17818.061567112825
        ],
        [
          2043,
          17818.065946400584
        ],
        [
          2044,
          17818.07028167358
        ],
        [
          2045,
          17818.07457866097
        ],
        [
          2046,
          17818.078876661435
        ],
        [
          2047,
          17818.083168086276
        ],
        [
          2048,
          17818.087469683258
        ],
        [
          2049,
          17818.0917727672
        ],
        [
          2050,
          17818.096081567794
        ],
        [
          2051,
          17818.110037689614
        ]
      ]
    },
    {
      "seriesName": "TRACO2INT",
      "seriesValues": [
        [
          2018,
          6.366462912410498e-12
        ],
        [
          2019,
          9.094947017729282e-12
        ],
        [
          2020,
          5.4569682106375694e-12
        ],
        [
          2021,
          5.070542101748288e-07
        ],
        [
          2022,
          5.070469342172146e-07
        ],
        [
          2023,
          5.070505721960217e-07
        ],
        [
          2024,
          5.070505721960217e-07
        ],
        [
          2025,
          5.070469342172146e-07
        ],
        [
          2026,
          5.070432962384075e-07
        ],
        [
          2027,
          5.070396582596004e-07
        ],
        [
          2028,
          5.070469342172146e-07
        ],
        [
          2029,
          5.070469342172146e-07
        ],
        [
          2030,
          5.070396582596004e-07
        ],
        [
          2031,
          5.070396582596004e-07
        ],
        [
          2032,
          5.070323823019862e-07
        ],
        [
          2033,
          5.070323823019862e-07
        ],
        [
          2034,
          5.07025106344372e-07
        ],
        [
          2035,
          5.070469342172146e-07
        ],
        [
          2036,
          5.070323823019862e-07
        ],
        [
          2037,
          5.070323823019862e-07
        ],
        [
          2038,
          5.070323823019862e-07
        ],
        [
          2039,
          5.070323823019862e-07
        ],
        [
          2040,
          5.070323823019862e-07
        ],
        [
          2041,
          5.070323823019862e-07
        ],
        [
          2042,
          5.070469342172146e-07
        ],
        [
          2043,
          5.070323823019862e-07
        ],
        [
          2044,
          5.070469342172146e-07
        ],
        [
          2045,
          5.070469342172146e-07
        ],
        [
          2046,
          5.070469342172146e-07
        ],
        [
          2047,
          5.070469342172146e-07
        ],
        [
          2048,
          5.07061486132443e-07
        ],
        [
          2049,
          5.07061486132443e-07
        ],
        [
          2050,
          5.07061486132443e-07
        ],
        [
          2051,
          5.070469342172146e-07
        ]
      ]
    },
    {
      "seriesName": "TRACO2N",
      "seriesValues": [
        [
          2018,
          12691.99288178
        ],
        [
          2019,
          24719.4745486152
        ],
        [
          2020,
          34905.3215438966
        ],
        [
          2021,
          45770.6357625942
        ],
        [
          2022,
          56507.0758017887
        ],
        [
          2023,
          67847.76864340159
        ],
        [
          2024,
          79669.940231913
        ],
        [
          2025,
          91584.4431323924
        ],
        [
          2026,
          102906.9323400132
        ],
        [
          2027,
          113180.654692521
        ],
        [
          2028,
          123134.85656730985
        ],
        [
          2029,
          132526.52276646643
        ],
        [
          2030,
          140908.4642402464
        ],
        [
          2031,
          148264.7824559325
        ],
        [
          2032,
          154634.42016080572
        ],
        [
          2033,
          159774.69425534495
        ],
        [
          2034,
          163529.35843328247
        ],
        [
          2035,
          165861.4697114346
        ],
        [
          2036,
          167397.48522118683
        ],
        [
          2037,
          168544.14398245368
        ],
        [
          2038,
          169424.28995390088
        ],
        [
          2039,
          170098.97702764088
        ],
        [
          2040,
          170647.8347429485
        ],
        [
          2041,
          171096.29743096247
        ],
        [
          2042,
          171472.93325468924
        ],
        [
          2043,
          171742.66785712546
        ],
        [
          2044,
          171947.4391926811
        ],
        [
          2045,
          172114.9021855503
        ],
        [
          2046,
          172246.47227157096
        ],
        [
          2047,
          172349.3560834539
        ],
        [
          2048,
          172423.0779715071
        ],
        [
          2049,
          172465.84612780347
        ],
        [
          2050,
          172494.98713896985
        ],
        [
          2051,
          172525.37590910427
        ]
      ]
    }
  ]
}